itemattribute/__init__.py
itemattribute/item_attribute.py
itemattribute/version.json
itemattribute-0.0.5.dist-info/LICENSE
itemattribute-0.0.5.dist-info/METADATA
itemattribute-0.0.5.dist-info/WHEEL
itemattribute-0.0.5.dist-info/top_level.txt
itemattribute-0.0.5.dist-info/RECORD
