Metadata-Version: 2.1
Name: itemattribute
Version: 0.0.5
Summary: Python class that allows dict item syntax for attribute access
Author-email: Andy Mounce <ammounce@gmail.com>
License: MIT License
Project-URL: Homepage, https://github.com/ammounce/itemattribute
Project-URL: Issues, https://github.com/ammounce/itemattribute/issues
Requires-Python: >=3.7
License-File: LICENSE
